mseep_mcp_server_weaviate-0.1.2.dist-info/licenses/LICENSE
src/__init__.py
src/server.py
src/settings.py
src/weaviate.py
mseep_mcp_server_weaviate-0.1.2.dist-info/METADATA
mseep_mcp_server_weaviate-0.1.2.dist-info/WHEEL
mseep_mcp_server_weaviate-0.1.2.dist-info/top_level.txt
mseep_mcp_server_weaviate-0.1.2.dist-info/RECORD
