Metadata-Version: 2.4
Name: mseep-mcp-server-weaviate
Version: 0.1.2
Summary: Add your description here
Home-page: 
Author: mseep
Author-email: mseep <support@skydeck.ai>
Maintainer-email: mseep <support@skydeck.ai>
Requires-Python: >=3.6
License-File: LICENSE
Requires-Dist: weaviate-client==4.10.4
Dynamic: author
Dynamic: license-file
Dynamic: requires-python
